config.py
main.py
yt_music_extractor-1.0.3.dist-info/licenses/LICENSE
yt_music_extractor-1.0.3.dist-info/METADATA
yt_music_extractor-1.0.3.dist-info/WHEEL
yt_music_extractor-1.0.3.dist-info/entry_points.txt
yt_music_extractor-1.0.3.dist-info/top_level.txt
yt_music_extractor-1.0.3.dist-info/RECORD
