Metadata-Version: 2.4
Name: yt-music-extractor
Version: 1.0.3
Summary: Download music from YouTube with proper metadata and album art, featuring parallel processing
Home-page: https://github.com/Captain-Vikram/YTMusic_To_M4A
Author: Vighnesh Kontham
Author-email: vighneshkontham@gmail.com
License: MIT
Keywords: youtube,music,download,metadata,album art,yt-dlp
Classifier: Development Status :: 4 - Beta
Classifier: Intended Audience :: End Users/Desktop
Classifier: Topic :: Multimedia :: Sound/Audio
Classifier: Programming Language :: Python :: 3
Classifier: Programming Language :: Python :: 3.7
Classifier: Programming Language :: Python :: 3.8
Classifier: Programming Language :: Python :: 3.9
Classifier: Programming Language :: Python :: 3.10
Classifier: Programming Language :: Python :: 3.11
Classifier: Programming Language :: Python :: 3.12
Classifier: Operating System :: OS Independent
Classifier: License :: OSI Approved :: MIT License
Requires-Python: >=3.7
License-File: LICENSE
Requires-Dist: yt-dlp>=2023.3.4
Requires-Dist: moviepy>=1.0.3
Requires-Dist: mutagen>=1.46.0
Requires-Dist: pillow>=9.4.0
Requires-Dist: requests>=2.28.2
Requires-Dist: setuptools>=67.7.2
Dynamic: author
Dynamic: author-email
Dynamic: classifier
Dynamic: description
Dynamic: description-content-type
Dynamic: home-page
Dynamic: keywords
Dynamic: license
Dynamic: license-file
Dynamic: requires-dist
Dynamic: requires-python
Dynamic: summary
